{"title": "Matryx - Creation", "version": 0, "width": 1, "height": 1, "is_menu": true, "effective_root": {"name": "Root", "enabled": true, "layer": 0, "layout_orientation": 0, "sizing_type": 0, "sizing_value": 0, "forward_dist": 0, "padding_type": 0, "padding_x": 0, "padding_y": 0, "padding_z": 0, "padding_w": 0, "content": null, "children": [{"name": "Top", "enabled": true, "layer": 0, "layout_orientation": 1, "sizing_type": 1, "sizing_value": 0.150000005960464, "forward_dist": 0, "padding_type": 0, "padding_x": 0, "padding_y": 0, "padding_z": 0, "padding_w": 0, "content": null, "children": [{"name": "Left", "enabled": true, "layer": 0, "layout_orientation": 0, "sizing_type": 1, "sizing_value": 0.150000005960464, "forward_dist": 0, "padding_type": 0, "padding_x": 0, "padding_y": 0, "padding_z": 0, "padding_w": 0, "content": null, "children": [{"name": "Parent", "enabled": true, "layer": 0, "layout_orientation": 0, "sizing_type": 0, "sizing_value": 0, "forward_dist": 0.0020000000949949, "padding_type": 0, "padding_x": 0, "padding_y": 0, "padding_z": 0.00999999977648258, "padding_w": 0.0750000029802322, "content": {"selected": false, "unusable": false, "text_active": true, "text_value_idle": "Parent", "text_value_selected": "Parent", "text_value_highlighted": "Parent", "text_value_selected_highlighted": "Parent", "text_value_unusable": "Parent", "text_auto_size": false, "text_min_size": 0, "text_max_size": 72, "text_size": 0.349999994039536, "text_underlined": false, "text_bolded": true, "text_vertical_align": 1, "text_horizontal_align": 1, "type_name": "Button"}, "children": []}]}, {"name": "Info", "enabled": true, "layer": 0, "layout_orientation": 0, "sizing_type": 0, "sizing_value": 0.100000001490116, "forward_dist": 0, "padding_type": 0, "padding_x": 0, "padding_y": 0, "padding_z": 0, "padding_w": 0, "content": null, "children": [{"name": "Address", "enabled": true, "layer": 0, "layout_orientation": 0, "sizing_type": 1, "sizing_value": 0.0500000007450581, "forward_dist": 0.0020000000949949, "padding_type": 0, "padding_x": 0, "padding_y": 0, "padding_z": 0, "padding_w": 0, "content": {"text": "0x1234abcd", "text_vertical_align": 1, "text_horizontal_align": 1, "text_auto_size": false, "text_min_size": 0, "text_max_size": 72, "text_size": 0.400000005960464, "text_color": -1, "text_bold": true, "text_italics": false, "text_underlined": false, "type_name": "Label"}, "children": []}, {"name": "Author", "enabled": true, "layer": 0, "layout_orientation": 0, "sizing_type": 1, "sizing_value": 0.0299999993294477, "forward_dist": 0.0020000000949949, "padding_type": 0, "padding_x": 0, "padding_y": 0, "padding_z": 0, "padding_w": 0, "content": {"text": "by c001...d00d", "text_vertical_align": 1, "text_horizontal_align": 1, "text_auto_size": false, "text_min_size": 0, "text_max_size": 72, "text_size": 0.300000011920929, "text_color": -1, "text_bold": true, "text_italics": false, "text_underlined": false, "type_name": "Label"}, "children": []}, {"name": "Time", "enabled": true, "layer": 0, "layout_orientation": 0, "sizing_type": 1, "sizing_value": 0.0700000002980232, "forward_dist": 0.0020000000949949, "padding_type": 0, "padding_x": 0, "padding_y": 0, "padding_z": 0, "padding_w": 0, "content": {"text": "on 3/3/2333 on 3:33PM", "text_vertical_align": 0, "text_horizontal_align": 1, "text_auto_size": false, "text_min_size": 0, "text_max_size": 72, "text_size": 0.300000011920929, "text_color": -1, "text_bold": true, "text_italics": false, "text_underlined": false, "type_name": "Label"}, "children": []}]}, {"name": "Right", "enabled": true, "layer": 0, "layout_orientation": 0, "sizing_type": 1, "sizing_value": 0.150000005960464, "forward_dist": 0, "padding_type": 0, "padding_x": 0, "padding_y": 0, "padding_z": 0, "padding_w": 0, "content": null, "children": []}]}, {"name": "Children", "enabled": true, "layer": 0, "layout_orientation": 0, "sizing_type": 1, "sizing_value": 0.699999988079071, "forward_dist": 0, "padding_type": 0, "padding_x": 0, "padding_y": 0, "padding_z": 0, "padding_w": 0, "content": null, "children": [{"name": "Children Label", "enabled": true, "layer": 0, "layout_orientation": 0, "sizing_type": 1, "sizing_value": 0.0750000029802322, "forward_dist": 0.0020000000949949, "padding_type": 0, "padding_x": 0, "padding_y": 0, "padding_z": 0, "padding_w": 0, "content": {"text": "Children", "text_vertical_align": 2, "text_horizontal_align": 1, "text_auto_size": false, "text_min_size": 0, "text_max_size": 72, "text_size": 0.400000005960464, "text_color": -1, "text_bold": true, "text_italics": false, "text_underlined": false, "type_name": "Label"}, "children": []}, {"name": "Children List", "enabled": true, "layer": 0, "layout_orientation": 0, "sizing_type": 0, "sizing_value": 0, "forward_dist": 0.0020000000949949, "padding_type": 0, "padding_x": 0, "padding_y": 0, "padding_z": 0, "padding_w": 0, "content": {"display_columns": 1, "display_rows": 5, "total_columns": 1, "unusable": false, "type_name": "List"}, "children": []}]}, {"name": "Bottom", "enabled": true, "layer": 0, "layout_orientation": 0, "sizing_type": 0, "sizing_value": 0.100000001490116, "forward_dist": 0, "padding_type": 0, "padding_x": 0, "padding_y": 0, "padding_z": 0, "padding_w": 0, "content": null, "children": [{"name": "View Files", "enabled": true, "layer": 0, "layout_orientation": 0, "sizing_type": 0, "sizing_value": 0, "forward_dist": 0.0020000000949949, "padding_type": 0, "padding_x": 0.330000013113022, "padding_y": 0.330000013113022, "padding_z": 0, "padding_w": 0, "content": {"selected": false, "unusable": false, "text_active": true, "text_value_idle": "View Files", "text_value_selected": "View Files", "text_value_highlighted": "View Files", "text_value_selected_highlighted": "View Files", "text_value_unusable": "View Files", "text_auto_size": false, "text_min_size": 0, "text_max_size": 72, "text_size": 0.5, "text_underlined": false, "text_bolded": true, "text_vertical_align": 1, "text_horizontal_align": 1, "type_name": "Button"}, "children": []}]}]}}